{"State.38eec7bf-8885-459f-a2df-e3106a727aee": {"id": "38eec7bf-8885-459f-a2df-e3106a727aee", "created_at": "2023-06-20T11:12:55.317187", "updated_at": "2023-06-20T08:12:55.317301", "name": "California", "__class__": "State"}, "State.cd7126d6-3b7b-45d5-8b4a-073b926c64fb": {"id": "cd7126d6-3b7b-45d5-8b4a-073b926c64fb", "created_at": "2023-06-20T11:12:55.318045", "updated_at": "2023-06-20T08:12:55.318098", "name": "Arizona", "__class__": "State"}, "State.7f780d61-0ff8-49f6-9b77-fdd5c1d8441a": {"id": "7f780d61-0ff8-49f6-9b77-fdd5c1d8441a", "created_at": "2023-06-20T11:25:37.394951", "updated_at": "2023-06-20T08:25:37.395053", "name": "California", "__class__": "State"}, "State.66508de4-eb52-424e-b4ba-2ef2845b4315": {"id": "66508de4-eb52-424e-b4ba-2ef2845b4315", "created_at": "2023-06-20T11:25:37.395886", "updated_at": "2023-06-20T08:25:37.395943", "name": "Arizona", "__class__": "State"}, "State.fe955f30-e1b9-43d4-bcfd-bac0062cd89f": {"id": "fe955f30-e1b9-43d4-bcfd-bac0062cd89f", "created_at": "2023-06-20T11:26:15.318731", "updated_at": "2023-06-20T08:26:15.318821", "name": "California", "__class__": "State"}, "State.476c4d1b-b75b-4cb2-a2c1-aa87b737e0d7": {"id": "476c4d1b-b75b-4cb2-a2c1-aa87b737e0d7", "created_at": "2023-06-20T11:26:15.319526", "updated_at": "2023-06-20T08:26:15.319578", "name": "Arizona", "__class__": "State"}, "Place.6674119b-c300-41cb-b64b-7a2b2ab1e8e3": {"id": "6674119b-c300-41cb-b64b-7a2b2ab1e8e3", "created_at": "2023-06-20T11:26:15.320829", "updated_at": "2023-06-20T08:26:15.320891", "city_id": "0001", "user_id": "0001", "name": "My little house", "number_rooms": 4, "number_bathrooms": 2, "max_guest": 10, "price_by_night": 300, "latitude": 37.773972, "longitude": -122.431297, "__class__": "Place"}, "State.f252196a-de06-4a82-a1d7-7bfcf53a169e": {"id": "f252196a-de06-4a82-a1d7-7bfcf53a169e", "created_at": "2023-06-20T13:56:11.649978", "updated_at": "2023-06-20T10:56:11.650099", "name": "California", "__class__": "State"}, "State.3d3222d2-031f-49a1-a9b5-d76c8c5971c9": {"id": "3d3222d2-031f-49a1-a9b5-d76c8c5971c9", "created_at": "2023-06-20T13:56:11.651017", "updated_at": "2023-06-20T10:56:11.651096", "name": "Arizona", "__class__": "State"}, "Place.17a67234-ccef-4545-8a1d-25e2f536a3ef": {"id": "17a67234-ccef-4545-8a1d-25e2f536a3ef", "created_at": "2023-06-20T13:56:11.652354", "updated_at": "2023-06-20T10:56:11.652437", "city_id": "0001", "user_id": "0001", "name": "My little house", "number_rooms": 4, "number_bathrooms": 2, "max_guest": 10, "price_by_night": 300, "latitude": 37.773972, "longitude": -122.431297, "__class__": "Place"}, "State.6880fe78-e0d4-4aab-9613-48ba93a491f7": {"id": "6880fe78-e0d4-4aab-9613-48ba93a491f7", "created_at": "2023-06-22T03:35:27.980883", "updated_at": "2023-06-22T03:35:27.980889", "name": "California", "__class__": "State"}, "State.08fa556c-3365-4c6d-880c-7996b617a4a8": {"id": "08fa556c-3365-4c6d-880c-7996b617a4a8", "created_at": "2023-06-22T03:35:27.981962", "updated_at": "2023-06-22T03:35:27.981968", "name": "Nevada", "__class__": "State"}}